Metadata-Version: 1.1
Name: spelchek
Version: 0.52
Summary: A pure-python Bayesian spellchecker
Home-page: https://github.com/theodox/spelchek
Author: Steve Theodore
Author-email: steve@theodox.com
License: MIT
Platform: UNKNOWN
Classifier: Development Status :: 5 - Production/Stable
Classifier: Intended Audience :: Developers
Classifier: Topic :: Text Processing
Classifier: Programming Language :: Python :: 2.7
Classifier: Programming Language :: Python :: 3
Classifier: Programming Language :: Python :: Implementation
